ci_board/__init__.py
ci_board/core/__init__.py
ci_board/core/context_cache.py
ci_board/core/executor.py
ci_board/core/message_pump_wrapper.py
ci_board/core/monitor.py
ci_board/core/source_tracker_.py
ci_board/core/source_tracker_wrapper.py
ci_board/handlers/__init__.py
ci_board/handlers/file_handler.py
ci_board/handlers/image_handler.py
ci_board/handlers/text_handler.py
ci_board/interfaces/__init__.py
ci_board/interfaces/callback_interface.py
ci_board/types/__init__.py
ci_board/types/t_clipboard.py
ci_board/types/t_image.py
ci_board/types/t_source.py
ci_board/utils/__init__.py
ci_board/utils/clipboard_reader.py
ci_board/utils/icon_extractor.py
ci_board/utils/logger.py
ci_board/utils/message_pump.py
ci_board/utils/win32_api.py
ci_board-0.1.4.dist-info/METADATA
ci_board-0.1.4.dist-info/WHEEL
ci_board-0.1.4.dist-info/top_level.txt
ci_board-0.1.4.dist-info/RECORD
