Metadata-Version: 2.4
Name: ci_board
Version: 0.1.4
Summary: A clipboard monitoring library for Windows
Author-email: StanleyUKN <stanley09537000@gmail.com>
Classifier: Programming Language :: Python :: 3
Classifier: License :: OSI Approved :: MIT License
Classifier: Operating System :: Microsoft :: Windows
Requires-Python: >=3.8
